customrag/__init__.py
customrag/rag_pipeline.py
customrag-0.1.2.dist-info/METADATA
customrag-0.1.2.dist-info/WHEEL
customrag-0.1.2.dist-info/entry_points.txt
customrag-0.1.2.dist-info/top_level.txt
customrag-0.1.2.dist-info/RECORD
