Metadata-Version: 2.4
Name: customrag
Version: 0.1.2
Summary: A customizable RAG pipeline supporting multiple LLM providers and embedding backends.
Author: Anuj Goel
Classifier: Programming Language :: Python :: 3
Classifier: Operating System :: OS Independent
Requires-Python: >=3.8
Requires-Dist: langchain
Requires-Dist: google-generativeai
Requires-Dist: openai
Requires-Dist: pyyaml
Requires-Dist: sentence-transformers
Requires-Dist: faiss-cpu
Requires-Dist: langchain-xai
Requires-Dist: huggingface-hub
Requires-Dist: pandas
Requires-Dist: pypdf
Requires-Dist: python-docx
Requires-Dist: langchain-community
Requires-Dist: langchain-google-genai
Dynamic: author
Dynamic: classifier
Dynamic: description
Dynamic: description-content-type
Dynamic: requires-dist
Dynamic: requires-python
Dynamic: summary
